{
    "asset": {
        "format": "jpg",
        "id": "11679d70eda8bc814f87f822b0621f25",
        "name": "34_00007_00001.jpg",
        "path": "file:/Users/duxtonlimyeecheng/Documents/Year%203%20Final%20Year/Final%20Year%20Project/TrainYOLO/TrainYourOwnYOLO/TrainJPG/34_00007_00001.jpg",
        "size": {
            "width": 29,
            "height": 29
        },
        "state": 2,
        "type": 1
    },
    "regions": [
        {
            "id": "3669K0vQJ",
            "type": "RECTANGLE",
            "tags": [
                "Turn left ahead"
            ],
            "boundingBox": {
                "height": 14.060177266293332,
                "width": 16.36917497675801,
                "left": 8.273398534757247,
                "top": 8.695933294247558
            },
            "points": [
                {
                    "x": 8.273398534757247,
                    "y": 8.695933294247558
                },
                {
                    "x": 24.64257351151526,
                    "y": 8.695933294247558
                },
                {
                    "x": 24.64257351151526,
                    "y": 22.75611056054089
                },
                {
                    "x": 8.273398534757247,
                    "y": 22.75611056054089
                }
            ]
        }
    ],
    "version": "2.2.0"
}