{
    "asset": {
        "format": "jpg",
        "id": "1b9534f952a24bda637f7c2991c79dae",
        "name": "28_00006_00019.jpg",
        "path": "file:/Users/duxtonlimyeecheng/Documents/Year%203%20Final%20Year/Final%20Year%20Project/TrainYOLO/TrainYourOwnYOLO/TrainJPG/28_00006_00019.jpg",
        "size": {
            "width": 63,
            "height": 57
        },
        "state": 2,
        "type": 1
    },
    "regions": [
        {
            "id": "QxRtmNs2q",
            "type": "RECTANGLE",
            "tags": [
                "Pedestrians"
            ],
            "boundingBox": {
                "height": 42.75550368467805,
                "width": 45.82852144646777,
                "left": 10.329071552608017,
                "top": 7.6871674082739485
            },
            "points": [
                {
                    "x": 10.329071552608017,
                    "y": 7.6871674082739485
                },
                {
                    "x": 56.15759299907579,
                    "y": 7.6871674082739485
                },
                {
                    "x": 56.15759299907579,
                    "y": 50.44267109295199
                },
                {
                    "x": 10.329071552608017,
                    "y": 50.44267109295199
                }
            ]
        }
    ],
    "version": "2.2.0"
}