{
    "asset": {
        "format": "jpg",
        "id": "2404edc6896cfb77643138028a09d0f1",
        "name": "38_00000_00017.jpg",
        "path": "file:/Users/duxtonlimyeecheng/Documents/Year%203%20Final%20Year/Final%20Year%20Project/TrainYOLO/TrainYourOwnYOLO/TrainJPG/38_00000_00017.jpg",
        "size": {
            "width": 46,
            "height": 46
        },
        "state": 2,
        "type": 1
    },
    "regions": [
        {
            "id": "ud2BxPrVG",
            "type": "RECTANGLE",
            "tags": [
                "Keep right"
            ],
            "boundingBox": {
                "height": 32.881649590123054,
                "width": 32.12586284633555,
                "left": 8.009102280707355,
                "top": 7.170552488488733
            },
            "points": [
                {
                    "x": 8.009102280707355,
                    "y": 7.170552488488733
                },
                {
                    "x": 40.1349651270429,
                    "y": 7.170552488488733
                },
                {
                    "x": 40.1349651270429,
                    "y": 40.052202078611785
                },
                {
                    "x": 8.009102280707355,
                    "y": 40.052202078611785
                }
            ]
        }
    ],
    "version": "2.2.0"
}