{
    "asset": {
        "format": "jpg",
        "id": "302f88d25932b04f475af414be3bab1f",
        "name": "30_00009_00011.jpg",
        "path": "file:/Users/duxtonlimyeecheng/Documents/Year%203%20Final%20Year/Final%20Year%20Project/TrainYOLO/TrainYourOwnYOLO/TrainJPG/30_00009_00011.jpg",
        "size": {
            "width": 54,
            "height": 50
        },
        "state": 2,
        "type": 1
    },
    "regions": [
        {
            "id": "VPt3JreZR",
            "type": "RECTANGLE",
            "tags": [
                "Beware of ice/snow"
            ],
            "boundingBox": {
                "height": 35.02634767370643,
                "width": 34.63882928449473,
                "left": 10.851223313143034,
                "top": 9.614803014176616
            },
            "points": [
                {
                    "x": 10.851223313143034,
                    "y": 9.614803014176616
                },
                {
                    "x": 45.49005259763777,
                    "y": 9.614803014176616
                },
                {
                    "x": 45.49005259763777,
                    "y": 44.64115068788305
                },
                {
                    "x": 10.851223313143034,
                    "y": 44.64115068788305
                }
            ]
        }
    ],
    "version": "2.2.0"
}