{
    "asset": {
        "format": "jpg",
        "id": "322f562b0383365ba43bade979308d15",
        "name": "23_00000_00022.jpg",
        "path": "file:/Users/duxtonlimyeecheng/Documents/Year%203%20Final%20Year/Final%20Year%20Project/TrainYOLO/TrainYourOwnYOLO/TrainJPG/23_00000_00022.jpg",
        "size": {
            "width": 56,
            "height": 54
        },
        "state": 2,
        "type": 1
    },
    "regions": [
        {
            "id": "2szA_Fbxv",
            "type": "RECTANGLE",
            "tags": [
                "Slippery road"
            ],
            "boundingBox": {
                "height": 42.22022163928834,
                "width": 46.61321390086207,
                "left": 4.584900323275862,
                "top": 7.7279408720832805
            },
            "points": [
                {
                    "x": 4.584900323275862,
                    "y": 7.7279408720832805
                },
                {
                    "x": 51.19811422413793,
                    "y": 7.7279408720832805
                },
                {
                    "x": 51.19811422413793,
                    "y": 49.94816251137161
                },
                {
                    "x": 4.584900323275862,
                    "y": 49.94816251137161
                }
            ]
        }
    ],
    "version": "2.2.0"
}