{
    "asset": {
        "format": "jpg",
        "id": "39d3b06236a9a41be1d9a099c1a65bec",
        "name": "30_00005_00011.jpg",
        "path": "file:/Users/duxtonlimyeecheng/Documents/Year%203%20Final%20Year/Final%20Year%20Project/TrainYOLO/TrainYourOwnYOLO/TrainJPG/30_00005_00011.jpg",
        "size": {
            "width": 43,
            "height": 39
        },
        "state": 2,
        "type": 1
    },
    "regions": [
        {
            "id": "8M_4gq2dy",
            "type": "RECTANGLE",
            "tags": [
                "Beware of ice/snow"
            ],
            "boundingBox": {
                "height": 21.52037461371417,
                "width": 25.2439182624428,
                "left": 9.0630713773061,
                "top": 9.731607439082051
            },
            "points": [
                {
                    "x": 9.0630713773061,
                    "y": 9.731607439082051
                },
                {
                    "x": 34.3069896397489,
                    "y": 9.731607439082051
                },
                {
                    "x": 34.3069896397489,
                    "y": 31.251982052796222
                },
                {
                    "x": 9.0630713773061,
                    "y": 31.251982052796222
                }
            ]
        }
    ],
    "version": "2.2.0"
}