{
    "asset": {
        "format": "jpg",
        "id": "47414f9c84e8d981de900b9435f6d0f0",
        "name": "15_00020_00011.jpg",
        "path": "file:/Users/duxtonlimyeecheng/Documents/Year%203%20Final%20Year/Final%20Year%20Project/TrainYOLO/TrainYourOwnYOLO/TrainJPG/15_00020_00011.jpg",
        "size": {
            "width": 33,
            "height": 35
        },
        "state": 2,
        "type": 1
    },
    "regions": [
        {
            "id": "5jipBjiza",
            "type": "RECTANGLE",
            "tags": [
                "No vehicles"
            ],
            "boundingBox": {
                "height": 22.1024616307696,
                "width": 20.921762385838466,
                "left": 6.082643651497325,
                "top": 7.263737835362934
            },
            "points": [
                {
                    "x": 6.082643651497325,
                    "y": 7.263737835362934
                },
                {
                    "x": 27.00440603733579,
                    "y": 7.263737835362934
                },
                {
                    "x": 27.00440603733579,
                    "y": 29.366199466132535
                },
                {
                    "x": 6.082643651497325,
                    "y": 29.366199466132535
                }
            ]
        }
    ],
    "version": "2.2.0"
}