{
    "asset": {
        "format": "jpg",
        "id": "58fed50a6f46efe60708e0d144865d4f",
        "name": "15_00001_00001.jpg",
        "path": "file:/Users/duxtonlimyeecheng/Documents/Year%203%20Final%20Year/Final%20Year%20Project/TrainYOLO/TrainYourOwnYOLO/TrainJPG/15_00001_00001.jpg",
        "size": {
            "width": 26,
            "height": 56
        },
        "state": 2,
        "type": 1
    },
    "regions": [
        {
            "id": "w2yIgPELp",
            "type": "RECTANGLE",
            "tags": [
                "No vehicles"
            ],
            "boundingBox": {
                "height": 38.772454703061165,
                "width": 14.624469866071427,
                "left": 6.0051339285714285,
                "top": 9.951674370770558
            },
            "points": [
                {
                    "x": 6.0051339285714285,
                    "y": 9.951674370770558
                },
                {
                    "x": 20.629603794642858,
                    "y": 9.951674370770558
                },
                {
                    "x": 20.629603794642858,
                    "y": 48.72412907383172
                },
                {
                    "x": 6.0051339285714285,
                    "y": 48.72412907383172
                }
            ]
        }
    ],
    "version": "2.2.0"
}