{
    "asset": {
        "format": "jpg",
        "id": "5f385a1b5ff2cf1987844c1b323b15f9",
        "name": "17_00020_00014.jpg",
        "path": "file:/Users/duxtonlimyeecheng/Documents/Year%203%20Final%20Year/Final%20Year%20Project/TrainYOLO/TrainYourOwnYOLO/TrainJPG/17_00020_00014.jpg",
        "size": {
            "width": 35,
            "height": 34
        },
        "state": 2,
        "type": 1
    },
    "regions": [
        {
            "id": "iYdz6xLYw",
            "type": "RECTANGLE",
            "tags": [
                "No entry"
            ],
            "boundingBox": {
                "height": 22.819619230400917,
                "width": 26.16517596774631,
                "left": 4.9622578091091585,
                "top": 7.743834015297816
            },
            "points": [
                {
                    "x": 4.9622578091091585,
                    "y": 7.743834015297816
                },
                {
                    "x": 31.12743377685547,
                    "y": 7.743834015297816
                },
                {
                    "x": 31.12743377685547,
                    "y": 30.563453245698735
                },
                {
                    "x": 4.9622578091091585,
                    "y": 30.563453245698735
                }
            ]
        }
    ],
    "version": "2.2.0"
}