{
    "asset": {
        "format": "jpg",
        "id": "609dadedb3fae142560194b14992be8a",
        "name": "01_00031_00014.jpg",
        "path": "file:/Users/duxtonlimyeecheng/Documents/Year%203%20Final%20Year/Final%20Year%20Project/TrainYOLO/TrainYourOwnYOLO/TrainJPG/01_00031_00014.jpg",
        "size": {
            "width": 42,
            "height": 42
        },
        "state": 2,
        "type": 1
    },
    "regions": [
        {
            "id": "tfLgJOdjX",
            "type": "RECTANGLE",
            "tags": [
                "Speed limit (30km/h)"
            ],
            "boundingBox": {
                "height": 25.294070687065087,
                "width": 31.10235215402356,
                "left": 5.894129128694778,
                "top": 7.60857256537682
            },
            "points": [
                {
                    "x": 5.894129128694778,
                    "y": 7.60857256537682
                },
                {
                    "x": 36.996481282718335,
                    "y": 7.60857256537682
                },
                {
                    "x": 36.996481282718335,
                    "y": 32.902643252441905
                },
                {
                    "x": 5.894129128694778,
                    "y": 32.902643252441905
                }
            ]
        }
    ],
    "version": "2.2.0"
}