{
    "asset": {
        "format": "jpg",
        "id": "6d2292856472f1cb386c4e5c7e57557d",
        "name": "02_00000_00023.jpg",
        "path": "file:/Users/duxtonlimyeecheng/Documents/Year%203%20Final%20Year/Final%20Year%20Project/TrainYOLO/TrainYourOwnYOLO/TrainJPG/02_00000_00023.jpg",
        "size": {
            "width": 64,
            "height": 63
        },
        "state": 2,
        "type": 1
    },
    "regions": [
        {
            "id": "06I2z8uLz",
            "type": "RECTANGLE",
            "tags": [
                "Speed limit (50km/h)"
            ],
            "boundingBox": {
                "height": 52.765070088184885,
                "width": 54.65017666457287,
                "left": 3.805869189698493,
                "top": 6.103142478249289
            },
            "points": [
                {
                    "x": 3.805869189698493,
                    "y": 6.103142478249289
                },
                {
                    "x": 58.456045854271366,
                    "y": 6.103142478249289
                },
                {
                    "x": 58.456045854271366,
                    "y": 58.868212566434174
                },
                {
                    "x": 3.805869189698493,
                    "y": 58.868212566434174
                }
            ]
        }
    ],
    "version": "2.2.0"
}