{
    "asset": {
        "format": "jpg",
        "id": "723fffc2d37597e24b154aa42fcd4002",
        "name": "33_00006_00005.jpg",
        "path": "file:/Users/duxtonlimyeecheng/Documents/Year%203%20Final%20Year/Final%20Year%20Project/TrainYOLO/TrainYourOwnYOLO/TrainJPG/33_00006_00005.jpg",
        "size": {
            "width": 30,
            "height": 30
        },
        "state": 2,
        "type": 1
    },
    "regions": [
        {
            "id": "8bKsnpAIY",
            "type": "RECTANGLE",
            "tags": [
                "Turn right ahead"
            ],
            "boundingBox": {
                "height": 18.19422533855497,
                "width": 18.958547590214824,
                "left": 5.9825868382517235,
                "top": 7.081084986872766
            },
            "points": [
                {
                    "x": 5.9825868382517235,
                    "y": 7.081084986872766
                },
                {
                    "x": 24.941134428466547,
                    "y": 7.081084986872766
                },
                {
                    "x": 24.941134428466547,
                    "y": 25.275310325427732
                },
                {
                    "x": 5.9825868382517235,
                    "y": 25.275310325427732
                }
            ]
        }
    ],
    "version": "2.2.0"
}