{
    "asset": {
        "format": "jpg",
        "id": "724ce41c73164d35818ec9b564567a27",
        "name": "01_00011_00025.jpg",
        "path": "file:/Users/duxtonlimyeecheng/Documents/Year%203%20Final%20Year/Final%20Year%20Project/TrainYOLO/TrainYourOwnYOLO/TrainJPG/01_00011_00025.jpg",
        "size": {
            "width": 73,
            "height": 71
        },
        "state": 2,
        "type": 1
    },
    "regions": [
        {
            "id": "UaiBdqqif",
            "type": "RECTANGLE",
            "tags": [
                "Speed limit (30km/h)"
            ],
            "boundingBox": {
                "height": 54.46337447979842,
                "width": 56.64349847090872,
                "left": 9.173225864989993,
                "top": 10.551717725058253
            },
            "points": [
                {
                    "x": 9.173225864989993,
                    "y": 10.551717725058253
                },
                {
                    "x": 65.81672433589871,
                    "y": 10.551717725058253
                },
                {
                    "x": 65.81672433589871,
                    "y": 65.01509220485667
                },
                {
                    "x": 9.173225864989993,
                    "y": 65.01509220485667
                }
            ]
        }
    ],
    "version": "2.2.0"
}