{
    "asset": {
        "format": "jpg",
        "id": "73a0ecf2ce5de503b837979ba7583f27",
        "name": "00_00002_00017.jpg",
        "path": "file:/Users/duxtonlimyeecheng/Documents/Year%203%20Final%20Year/Final%20Year%20Project/TrainYOLO/TrainYourOwnYOLO/TrainJPG/00_00002_00017.jpg",
        "size": {
            "width": 46,
            "height": 45
        },
        "state": 2,
        "type": 1
    },
    "regions": [
        {
            "id": "8JzEIw0Cu",
            "type": "RECTANGLE",
            "tags": [
                "Speed limit (20km/h)"
            ],
            "boundingBox": {
                "height": 33.221970305866556,
                "width": 36.57888205544455,
                "left": 6.387690922358891,
                "top": 5.9732702487092215
            },
            "points": [
                {
                    "x": 6.387690922358891,
                    "y": 5.9732702487092215
                },
                {
                    "x": 42.966572977803445,
                    "y": 5.9732702487092215
                },
                {
                    "x": 42.966572977803445,
                    "y": 39.195240554575776
                },
                {
                    "x": 6.387690922358891,
                    "y": 39.195240554575776
                }
            ]
        }
    ],
    "version": "2.2.0"
}