{
    "asset": {
        "format": "jpg",
        "id": "8c604847bb570885bf25a92a8fd1f7e5",
        "name": "35_00021_00025.jpg",
        "path": "file:/Users/duxtonlimyeecheng/Documents/Year%203%20Final%20Year/Final%20Year%20Project/TrainYOLO/TrainYourOwnYOLO/TrainJPG/35_00021_00025.jpg",
        "size": {
            "width": 74,
            "height": 74
        },
        "state": 2,
        "type": 1
    },
    "regions": [
        {
            "id": "Fny9Sl0C-",
            "type": "RECTANGLE",
            "tags": [
                "Ahead only"
            ],
            "boundingBox": {
                "height": 53.98029967201864,
                "width": 59.885710080139965,
                "left": 6.380705446705024,
                "top": 11.909346396394598
            },
            "points": [
                {
                    "x": 6.380705446705024,
                    "y": 11.909346396394598
                },
                {
                    "x": 66.266415526845,
                    "y": 11.909346396394598
                },
                {
                    "x": 66.266415526845,
                    "y": 65.88964606841324
                },
                {
                    "x": 6.380705446705024,
                    "y": 65.88964606841324
                }
            ]
        }
    ],
    "version": "2.2.0"
}