{
    "asset": {
        "format": "jpg",
        "id": "8e44a2628504ff0109067849405589ed",
        "name": "14_00014_00014.jpg",
        "path": "file:/Users/duxtonlimyeecheng/Documents/Year%203%20Final%20Year/Final%20Year%20Project/TrainYOLO/TrainYourOwnYOLO/TrainJPG/14_00014_00014.jpg",
        "size": {
            "width": 65,
            "height": 75
        },
        "state": 2,
        "type": 1
    },
    "regions": [
        {
            "id": "KmyRRWjTW",
            "type": "RECTANGLE",
            "tags": [
                "Stop"
            ],
            "boundingBox": {
                "height": 60.46286827453676,
                "width": 50.929761202830186,
                "left": 9.106678512861144,
                "top": 7.438619923421141
            },
            "points": [
                {
                    "x": 9.106678512861144,
                    "y": 7.438619923421141
                },
                {
                    "x": 60.03643971569133,
                    "y": 7.438619923421141
                },
                {
                    "x": 60.03643971569133,
                    "y": 67.9014881979579
                },
                {
                    "x": 9.106678512861144,
                    "y": 67.9014881979579
                }
            ]
        }
    ],
    "version": "2.2.0"
}