{
    "asset": {
        "format": "jpg",
        "id": "96774bb80e5175c3c89eeaf242d27552",
        "name": "36_00002_00023.jpg",
        "path": "file:/Users/duxtonlimyeecheng/Documents/Year%203%20Final%20Year/Final%20Year%20Project/TrainYOLO/TrainYourOwnYOLO/TrainJPG/36_00002_00023.jpg",
        "size": {
            "width": 70,
            "height": 70
        },
        "state": 2,
        "type": 1
    },
    "regions": [
        {
            "id": "2h8BkTEx6",
            "type": "RECTANGLE",
            "tags": [
                "Go straight or right"
            ],
            "boundingBox": {
                "height": 56.3465775362196,
                "width": 57.01893261918252,
                "left": 7.795015516271387,
                "top": 6.804715586146978
            },
            "points": [
                {
                    "x": 7.795015516271387,
                    "y": 6.804715586146978
                },
                {
                    "x": 64.81394813545391,
                    "y": 6.804715586146978
                },
                {
                    "x": 64.81394813545391,
                    "y": 63.151293122366575
                },
                {
                    "x": 7.795015516271387,
                    "y": 63.151293122366575
                }
            ]
        }
    ],
    "version": "2.2.0"
}