{
    "asset": {
        "format": "jpg",
        "id": "be632450abbf7bfc8deaf2bd28c42f15",
        "name": "26_00006_00028.jpg",
        "path": "file:/Users/duxtonlimyeecheng/Documents/Year%203%20Final%20Year/Final%20Year%20Project/TrainYOLO/TrainYourOwnYOLO/TrainJPG/26_00006_00028.jpg",
        "size": {
            "width": 94,
            "height": 87
        },
        "state": 2,
        "type": 1
    },
    "regions": [
        {
            "id": "TIbtz0pfv",
            "type": "RECTANGLE",
            "tags": [
                "Traffic signals"
            ],
            "boundingBox": {
                "height": 70.26715109711161,
                "width": 78.42360279104885,
                "left": 6.117631591335361,
                "top": 9.955635764382103
            },
            "points": [
                {
                    "x": 6.117631591335361,
                    "y": 9.955635764382103
                },
                {
                    "x": 84.54123438238422,
                    "y": 9.955635764382103
                },
                {
                    "x": 84.54123438238422,
                    "y": 80.22278686149372
                },
                {
                    "x": 6.117631591335361,
                    "y": 80.22278686149372
                }
            ]
        }
    ],
    "version": "2.2.0"
}