{
    "asset": {
        "format": "jpg",
        "id": "d6666a8d053e4ea3baeb135b3464acb6",
        "name": "34_00005_00026.jpg",
        "path": "file:/Users/duxtonlimyeecheng/Documents/Year%203%20Final%20Year/Final%20Year%20Project/TrainYOLO/TrainYourOwnYOLO/TrainJPG/34_00005_00026.jpg",
        "size": {
            "width": 52,
            "height": 60
        },
        "state": 2,
        "type": 1
    },
    "regions": [
        {
            "id": "8Fe6KeQud",
            "type": "RECTANGLE",
            "tags": [
                "Turn left ahead"
            ],
            "boundingBox": {
                "height": 40.72441062108976,
                "width": 42.13112366874263,
                "left": 7.364254357679835,
                "top": 10.899997356597932
            },
            "points": [
                {
                    "x": 7.364254357679835,
                    "y": 10.899997356597932
                },
                {
                    "x": 49.495378026422465,
                    "y": 10.899997356597932
                },
                {
                    "x": 49.495378026422465,
                    "y": 51.624407977687696
                },
                {
                    "x": 7.364254357679835,
                    "y": 51.624407977687696
                }
            ]
        }
    ],
    "version": "2.2.0"
}