{
    "asset": {
        "format": "jpg",
        "id": "d6c30d22d6861249fe2d605dd1639b8a",
        "name": "36_00000_00008.jpg",
        "path": "file:/Users/duxtonlimyeecheng/Documents/Year%203%20Final%20Year/Final%20Year%20Project/TrainYOLO/TrainYourOwnYOLO/TrainJPG/36_00000_00008.jpg",
        "size": {
            "width": 39,
            "height": 39
        },
        "state": 2,
        "type": 1
    },
    "regions": [
        {
            "id": "g7PE1Iizt",
            "type": "RECTANGLE",
            "tags": [
                "Go straight or right"
            ],
            "boundingBox": {
                "height": 27.736626193520973,
                "width": 29.383252152627044,
                "left": 3.4086136004532688,
                "top": 6.392400256459877
            },
            "points": [
                {
                    "x": 3.4086136004532688,
                    "y": 6.392400256459877
                },
                {
                    "x": 32.791865753080316,
                    "y": 6.392400256459877
                },
                {
                    "x": 32.791865753080316,
                    "y": 34.12902644998085
                },
                {
                    "x": 3.4086136004532688,
                    "y": 34.12902644998085
                }
            ]
        }
    ],
    "version": "2.2.0"
}