{
    "asset": {
        "format": "jpg",
        "id": "d9a64b054cc6a2b1c31e0706b4d4727c",
        "name": "38_00009_00028.jpg",
        "path": "file:/Users/duxtonlimyeecheng/Documents/Year%203%20Final%20Year/Final%20Year%20Project/TrainYOLO/TrainYourOwnYOLO/TrainJPG/38_00009_00028.jpg",
        "size": {
            "width": 71,
            "height": 76
        },
        "state": 2,
        "type": 1
    },
    "regions": [
        {
            "id": "es1s_M4hi",
            "type": "RECTANGLE",
            "tags": [
                "Keep right"
            ],
            "boundingBox": {
                "height": 61.20792452039709,
                "width": 61.654396532402664,
                "left": 6.578768037056011,
                "top": 9.354831839728039
            },
            "points": [
                {
                    "x": 6.578768037056011,
                    "y": 9.354831839728039
                },
                {
                    "x": 68.23316456945867,
                    "y": 9.354831839728039
                },
                {
                    "x": 68.23316456945867,
                    "y": 70.56275636012514
                },
                {
                    "x": 6.578768037056011,
                    "y": 70.56275636012514
                }
            ]
        }
    ],
    "version": "2.2.0"
}