{
    "asset": {
        "format": "jpg",
        "id": "debfb30d49829982ee88ccc8adb86878",
        "name": "29_00002_00008.jpg",
        "path": "file:/Users/duxtonlimyeecheng/Documents/Year%203%20Final%20Year/Final%20Year%20Project/TrainYOLO/TrainYourOwnYOLO/TrainJPG/29_00002_00008.jpg",
        "size": {
            "width": 41,
            "height": 40
        },
        "state": 2,
        "type": 1
    },
    "regions": [
        {
            "id": "KMrb8Dzo-",
            "type": "RECTANGLE",
            "tags": [
                "Bicycles crossing"
            ],
            "boundingBox": {
                "height": 25.637622244876788,
                "width": 31.69384954268055,
                "left": 5.598370598653259,
                "top": 8.535933061079545
            },
            "points": [
                {
                    "x": 5.598370598653259,
                    "y": 8.535933061079545
                },
                {
                    "x": 37.29222014133381,
                    "y": 8.535933061079545
                },
                {
                    "x": 37.29222014133381,
                    "y": 34.173555305956334
                },
                {
                    "x": 5.598370598653259,
                    "y": 34.173555305956334
                }
            ]
        }
    ],
    "version": "2.2.0"
}